streamlit_imp_new_scenario/__init__.py
streamlit_imp_new_scenario/frontend/build/asset-manifest.json
streamlit_imp_new_scenario/frontend/build/bootstrap.min.css
streamlit_imp_new_scenario/frontend/build/index.html
streamlit_imp_new_scenario/frontend/build/static/css/main.8eb19db9.css
streamlit_imp_new_scenario/frontend/build/static/css/main.8eb19db9.css.map
streamlit_imp_new_scenario/frontend/build/static/custom_css/custom.css
streamlit_imp_new_scenario/frontend/build/static/images/browse.png
streamlit_imp_new_scenario/frontend/build/static/images/download_icon.png
streamlit_imp_new_scenario/frontend/build/static/images/image 1.png
streamlit_imp_new_scenario/frontend/build/static/images/imperial.png
streamlit_imp_new_scenario/frontend/build/static/images/logo.PNG
streamlit_imp_new_scenario/frontend/build/static/images/optimisation_target.png
streamlit_imp_new_scenario/frontend/build/static/images/order_icon.png
streamlit_imp_new_scenario/frontend/build/static/images/plus_icon.png
streamlit_imp_new_scenario/frontend/build/static/images/question_mark.png
streamlit_imp_new_scenario/frontend/build/static/images/scenario_name_icon.png
streamlit_imp_new_scenario/frontend/build/static/images/sidebar.png
streamlit_imp_new_scenario/frontend/build/static/images/upload.png
streamlit_imp_new_scenario/frontend/build/static/images/upload_input_data.png
streamlit_imp_new_scenario/frontend/build/static/js/main.4b4209d0.js
streamlit_imp_new_scenario/frontend/build/static/js/main.4b4209d0.js.LICENSE.txt
streamlit_imp_new_scenario/frontend/build/static/js/main.4b4209d0.js.map
streamlit_imp_new_scenario-2.0.1.dist-info/LICENSE
streamlit_imp_new_scenario-2.0.1.dist-info/METADATA
streamlit_imp_new_scenario-2.0.1.dist-info/WHEEL
streamlit_imp_new_scenario-2.0.1.dist-info/top_level.txt
streamlit_imp_new_scenario-2.0.1.dist-info/RECORD
