Metadata-Version: 2.1
Name: streamlit-imp-new-scenario
Version: 2.0.1
Summary: UNKNOWN
Home-page: UNKNOWN
Author: 
Author-email: 
License: UNKNOWN
Platform: UNKNOWN
Requires-Python: >=3.6
Requires-Dist: streamlit (>=1.36)
